valenspy/__init__.py
valenspy/_utilities/__init__.py
valenspy/_utilities/_regions.py
valenspy/_utilities/_utilities.py
valenspy/_utilities/cf_checks.py
valenspy/_utilities/unit_converter.py
valenspy/ancilliary_data/ALARO-SFX_K_lookup.yml
valenspy/ancilliary_data/CCLM_lookup.yml
valenspy/ancilliary_data/CLIMATE_GRID_lookup.yml
valenspy/ancilliary_data/CORDEX_variables.yml
valenspy/ancilliary_data/EOBS_lookup.yml
valenspy/ancilliary_data/ERA5_lookup.yml
valenspy/ancilliary_data/MAR_lookup.yml
valenspy/ancilliary_data/RADCLIM_lookup.yml
valenspy/ancilliary_data/dataset_PATHS.yml
valenspy/diagnostic/__init__.py
valenspy/diagnostic/_ensemble2ref.py
valenspy/diagnostic/_ensemble2self.py
valenspy/diagnostic/_model2ref.py
valenspy/diagnostic/_model2self.py
valenspy/diagnostic/diagnostic.py
valenspy/diagnostic/functions.py
valenspy/diagnostic/plot_utils.py
valenspy/diagnostic/visualizations.py
valenspy/diagnostic/wrappers.py
valenspy/input/__init__.py
valenspy/input/converter.py
valenspy/input/converter_functions.py
valenspy/input/manager.py
valenspy/processing/__init__.py
valenspy/processing/indicators.py
valenspy/processing/mask.py
valenspy/processing/regrid.py
valenspy/processing/select.py
valenspy/processing/units.py
valenspy-0.3.2.dist-info/LICENSE
valenspy-0.3.2.dist-info/METADATA
valenspy-0.3.2.dist-info/WHEEL
valenspy-0.3.2.dist-info/RECORD
