Metadata-Version: 2.1
Name: ValEnsPy
Version: 0.3.2
Summary: A Python package to validate gridded model data.
Home-page: https://github.com/CORDEX-be2/ValEnsPy
License: GPL-3.0
Keywords: validation,ensemble,climate,meteorology,model,data
Author: Kobe Vandelanotte
Author-email: kobe.vandelanotte@meteo.be
Maintainer: Kobe Vandelanotte
Maintainer-email: kobe.vandelanotte@meteo.be
Requires-Python: >=3.10,<4.0
Classifier: Development Status :: 3 - Alpha
Classifier: Intended Audience :: Science/Research
Classifier: License :: OSI Approved :: GNU General Public License v3 (GPLv3)
Classifier: Natural Language :: English
Classifier: Operating System :: OS Independent
Classifier: Programming Language :: Python :: 3
Classifier: Programming Language :: Python :: 3.10
Classifier: Programming Language :: Python :: 3.11
Classifier: Programming Language :: Python :: 3.12
Classifier: Topic :: Scientific/Engineering :: Atmospheric Science
Requires-Dist: cartopy (>=0.23.0,<0.24.0)
Requires-Dist: cf-xarray (>=0.9.4)
Requires-Dist: dask (>=2024.3.1,<2025.0.0)
Requires-Dist: docstring-parser (>=0.16,<0.17)
Requires-Dist: geopandas (>=1.0.1,<2.0.0)
Requires-Dist: matplotlib (>=3.8.3,<4.0.0)
Requires-Dist: nc-time-axis (>=1.4.1,<2.0.0)
Requires-Dist: netCDF4 (>=1.6.5,<2.0.0)
Requires-Dist: pandas (>=2.2.1,<3.0.0)
Requires-Dist: pooch (>=1.8.1,<2.0.0)
Requires-Dist: regionmask (>=0.12.1,<0.13.0)
Requires-Dist: scipy (>=1.13.0,<2.0.0)
Requires-Dist: seaborn (>=0.13.2,<0.14.0)
Requires-Dist: shapely (>=2.0.3,<3.0.0)
Requires-Dist: xarray (>=2023.12.0,<=2024.07.0)
Requires-Dist: xarray-datatree (==0.0.14)
Requires-Dist: xclim (>=0.54.0,<0.55.0)
Requires-Dist: xesmf (>=0.8.8,<0.9.0)
Project-URL: Documentation, https://cordex-be2.github.io/ValEnsPy/
Project-URL: Repository, https://github.com/CORDEX-be2/ValEnsPy
